telemetry_parser-0.3.0.dist-info/METADATA
telemetry_parser-0.3.0.dist-info/WHEEL
telemetry_parser/__init__.py
telemetry_parser/telemetry_parser.cpython-310-i386-linux-gnu.so
telemetry_parser-0.3.0.dist-info/RECORD
